tkscrolledframe/__init__.py
tkscrolledframe/__main__.py
tkscrolledframe/widget.py
tkScrolledFrame-1.0.4.dist-info/LICENSE
tkScrolledFrame-1.0.4.dist-info/METADATA
tkScrolledFrame-1.0.4.dist-info/WHEEL
tkScrolledFrame-1.0.4.dist-info/top_level.txt
tkScrolledFrame-1.0.4.dist-info/RECORD
