Metadata-Version: 2.1
Name: tkScrolledFrame
Version: 1.0.4
Summary: Scrollable frame widget for Tkinter
Home-page: https://github.com/bmjcode/tkScrolledFrame
Author: Benjamin Johnson
Author-email: bmjcode@gmail.com
License: UNKNOWN
Platform: UNKNOWN
Classifier: Development Status :: 4 - Beta
Classifier: Programming Language :: Python :: 2
Classifier: Programming Language :: Python :: 3
Classifier: License :: OSI Approved :: MIT License
Classifier: Operating System :: OS Independent
